coordinate_system/__init__.py
coordinate_system/complex_geometric_physics.py
coordinate_system/coordinate_system.cp313-win_amd64.pyd
coordinate_system/curve_interpolation.py
coordinate_system/differential_geometry.py
coordinate_system/spectral_geometry.py
coordinate_system/u3_frame.py
coordinate_system/visualization.py
coordinate_system-7.0.1.dist-info/LICENSE
coordinate_system-7.0.1.dist-info/METADATA
coordinate_system-7.0.1.dist-info/WHEEL
coordinate_system-7.0.1.dist-info/top_level.txt
coordinate_system-7.0.1.dist-info/RECORD
