Metadata-Version: 2.1
Name: coordinate_system
Version: 7.0.1
Summary: High-performance 3D coordinate system library with unified differential geometry, quantum frame algebra, and Christmas Equation (CFUT)
Home-page: https://github.com/panguojun/Coordinate-System
Author: PanGuoJun
Author-email: PanGuoJun <18858146@qq.com>
License: MIT
Project-URL: Homepage, https://github.com/panguojun/Coordinate-System
Project-URL: Documentation, https://github.com/panguojun/Coordinate-System/blob/main/README.md
Project-URL: Repository, https://github.com/panguojun/Coordinate-System
Project-URL: Bug Reports, https://github.com/panguojun/Coordinate-System/issues
Project-URL: DOI, https://zenodo.org/records/14435613
Keywords: 3d,math,vector,quaternion,coordinate-system,geometry,differential-geometry,curvature,spectral-analysis,christmas-equation,cfut,unified-field-theory,complex-frame
Platform: Windows
Platform: Linux
Platform: macOS
Platform: Android
Platform: iOS
Classifier: Development Status :: 5 - Production/Stable
Classifier: Intended Audience :: Developers
Classifier: Intended Audience :: Science/Research
Classifier: Topic :: Software Development :: Libraries :: Python Modules
Classifier: Topic :: Scientific/Engineering :: Mathematics
Classifier: Topic :: Scientific/Engineering :: Physics
Classifier: License :: OSI Approved :: MIT License
Classifier: Programming Language :: Python :: 3
Classifier: Programming Language :: Python :: 3.7
Classifier: Programming Language :: Python :: 3.8
Classifier: Programming Language :: Python :: 3.9
Classifier: Programming Language :: Python :: 3.10
Classifier: Programming Language :: Python :: 3.11
Classifier: Programming Language :: Python :: 3.12
Classifier: Programming Language :: Python :: 3.13
Classifier: Programming Language :: C++
Classifier: Operating System :: Microsoft :: Windows
Classifier: Operating System :: POSIX :: Linux
Classifier: Operating System :: MacOS
Requires-Python: >=3.7
License-File: LICENSE
Requires-Dist: numpy>=1.19.0
Requires-Dist: matplotlib>=3.3.0
